{"id":"App.vue","dependencies":[{"name":"F:\\host\\person\\vue-layer\\package.json","includedInParent":true,"mtime":1535353509811},{"name":"F:\\host\\person\\vue-layer\\.babelrc","includedInParent":true,"mtime":1535353309558},{"name":"babel-runtime/regenerator","parent":"F:\\host\\person\\vue-layer\\demo\\App.vue","resolved":"F:\\host\\person\\vue-layer\\node_modules\\babel-runtime\\regenerator\\index.js"},{"name":"babel-runtime/helpers/asyncToGenerator","parent":"F:\\host\\person\\vue-layer\\demo\\App.vue","resolved":"F:\\host\\person\\vue-layer\\node_modules\\babel-runtime\\helpers\\asyncToGenerator.js"},{"name":"./js/tools.js","parent":"F:\\host\\person\\vue-layer\\demo\\App.vue","resolved":"F:\\host\\person\\vue-layer\\demo\\js\\tools.js"},{"name":"./form.vue","parent":"F:\\host\\person\\vue-layer\\demo\\App.vue","resolved":"F:\\host\\person\\vue-layer\\demo\\form.vue"},{"name":"_css_loader","parent":"F:\\host\\person\\vue-layer\\demo\\App.vue","resolved":"F:\\host\\person\\vue-layer\\node_modules\\parcel-bundler\\src\\builtins\\css-loader.js"},{"name":"vue-hot-reload-api","parent":"F:\\host\\person\\vue-layer\\demo\\App.vue","resolved":"F:\\host\\person\\vue-layer\\node_modules\\vue-hot-reload-api\\dist\\index.js"},{"name":"vue","parent":"F:\\host\\person\\vue-layer\\demo\\App.vue","resolved":"F:\\host\\person\\vue-layer\\node_modules\\vue\\dist\\vue.runtime.esm.js"}],"generated":{"js":"\"use strict\";\n\nObject.defineProperty(exports, \"__esModule\", {\n  value: true\n});\n\nvar _regenerator = require(\"babel-runtime/regenerator\");\n\nvar _regenerator2 = _interopRequireDefault(_regenerator);\n\nvar _asyncToGenerator2 = require(\"babel-runtime/helpers/asyncToGenerator\");\n\nvar _asyncToGenerator3 = _interopRequireDefault(_asyncToGenerator2);\n\nvar _tools = require(\"./js/tools.js\");\n\nvar _tools2 = _interopRequireDefault(_tools);\n\nvar _form = require(\"./form.vue\");\n\nvar _form2 = _interopRequireDefault(_form);\n\nfunction _interopRequireDefault(obj) { return obj && obj.__esModule ? obj : { default: obj }; }\n\n//\n//\n//\n//\n//\n//\n//\n//\n//\n//\n//\n//\n//\n//\n//\n//\n//\n//\n//\n//\n//\n//\n//\n//\n//\n//\n//\n//\n//\n//\n//\n//\n//\n//\n//\n//\n//\n//\n//\n//\n//\n//\n//\n//\n//\n//\n//\n//\n//\n//\n//\n//\n//\n//\n//\n//\n//\n//\n//\n//\n//\n//\n//\n//\n//\n//\n//\n//\n//\n//\n//\n//\n//\n//\n//\n\nexports.default = {\n  data: function data() {\n    return {};\n  },\n\n  components: {\n    \"base-form\": _form2.default\n  },\n  mounted: function () {\n    var _ref = (0, _asyncToGenerator3.default)(_regenerator2.default.mark(function _callee() {\n      var ids, i, id, _i;\n\n      return _regenerator2.default.wrap(function _callee$(_context) {\n        while (1) {\n          switch (_context.prev = _context.next) {\n            case 0:\n              ids = [];\n              i = 0;\n\n            case 2:\n              if (!(i < 5)) {\n                _context.next = 10;\n                break;\n              }\n\n              _context.next = 5;\n              return _tools2.default.sleep(10);\n\n            case 5:\n              id = this.loadingHandle();\n\n              ids.push(id);\n\n            case 7:\n              i++;\n              _context.next = 2;\n              break;\n\n            case 10:\n              _i = 0;\n\n            case 11:\n              if (!(_i < 5)) {\n                _context.next = 18;\n                break;\n              }\n\n              _context.next = 14;\n              return _tools2.default.sleep(200);\n\n            case 14:\n              this.$layer.close(ids[_i]);\n\n            case 15:\n              _i++;\n              _context.next = 11;\n              break;\n\n            case 18:\n              this.$on(\"asd\", function (val) {\n                this.$layer.msg(val);\n              });\n\n            case 19:\n            case \"end\":\n              return _context.stop();\n          }\n        }\n      }, _callee, this);\n    }));\n\n    function mounted() {\n      return _ref.apply(this, arguments);\n    }\n\n    return mounted;\n  }(),\n\n  methods: {\n    submitHandle: function submitHandle() {\n      var _this = this;\n\n      var id = this.$layer.alert(\"this is demo!!!<br/>this is demo!!!<br/>this is demo!!!<br/>this is demo!!!<br/>this is demo!!!<br/>this is demo!!!<br/>this is demo!!!<br/>this is demo!!!this is demo!!!this is demo!!!this is demo!!!this is demo!!!this is demo!!!this is demo!!!this is demo!!!this is demo!!!\", {\n        shade: true\n      }, function () {\n        alert(1);\n        _this.$layer.close(id);\n      });\n    },\n    confirmHandle: function confirmHandle() {\n      var _this2 = this;\n\n      var id = this.$layer.confirm(\"确定要<br/>删除吗？\", function () {\n        _this2.$layer.msg(\"执行了删除\");\n        _this2.$layer.close(id);\n      }, function () {\n        _this2.$layer.msg(\"执行取消\");\n        _this2.$layer.close(id);\n      });\n    },\n    msgHandle: function msgHandle() {\n      var id = this.$layer.msg(\"弱弱的提示\");\n    },\n    msg1Handle: function msg1Handle() {\n      var _this3 = this;\n\n      var id = this.$layer.msg(\"5s后刷新页面\", {\n        time: 5\n      }, function () {\n        _this3.$layer.close(id);\n      });\n    },\n    loadingHandle: function loadingHandle() {\n      var id = this.$layer.loading({\n        time: 500\n      });\n      return id;\n    },\n    tipsHandle: function tipsHandle() {\n      var id = this.$layer.tips(\"在很久很久以前\", \"#tips\", {\n        tips: 0,\n        time: 100\n      });\n    },\n    tips1Handle: function tips1Handle() {\n      var id = this.$layer.tips(\"在很久很久以前，在很久很久以前，在很久很久以前，在很久很久以前，在很久很久以前，在很久很久以前，\", \"#tips1\", {\n        tips: 1,\n        time: 100\n      });\n    },\n    tips2Handle: function tips2Handle() {\n      var id = this.$layer.tips(\"在很久很久以前，在很久很久以前，在很久很久以前，在很久很久以前，在很久很久以前，在很久很久以前，\", \"#tips2\", {\n        tips: 2\n      });\n    },\n    tips3Handle: function tips3Handle() {\n      var id = this.$layer.tips(\"在很久很久以前，在很久很久以前，在很久很久以前，在很久很久以前，在很久很久以前，在很久很久以前，\", \"#tips3\", {\n        tips: [3, {\n          selfa: true\n        }],\n        time: 10\n      });\n    },\n    pageHandle: function pageHandle() {\n      var ids = this.$layer.iframe({\n        content: {\n          content: _form2.default,\n          parent: this,\n          data: {\n            check: \"aaaaaaaaxxxx\"\n          }\n        },\n        area: [\"900px\", \"600px\"],\n        title: \"\",\n        shade: false\n      });\n    }\n  }\n};\n        var $f800f7 = exports.default || module.exports;\n      \n      if (typeof $f800f7 === 'function') {\n        $f800f7 = $f800f7.options;\n      }\n    \n        /* template */\n        Object.assign($f800f7, (function () {\n          var render = function() {\n  var _vm = this\n  var _h = _vm.$createElement\n  var _c = _vm._self._c || _h\n  return _c(\n    \"div\",\n    {\n      staticStyle: { width: \"1000px\", margin: \"100px auto\" },\n      attrs: { id: \"app\" }\n    },\n    [\n      _c(\"br\"),\n      _vm._v(\" \"),\n      _c(\"br\"),\n      _vm._v(\" \"),\n      _c(\"br\"),\n      _vm._v(\" \"),\n      _c(\"br\"),\n      _vm._v(\" \"),\n      _c(\"br\"),\n      _vm._v(\" \"),\n      _c(\"br\"),\n      _vm._v(\" \"),\n      _c(\"br\"),\n      _vm._v(\" \"),\n      _c(\"br\"),\n      _vm._v(\" \"),\n      _c(\"br\"),\n      _vm._v(\" \"),\n      _c(\"br\"),\n      _vm._v(\" \"),\n      _c(\"br\"),\n      _vm._v(\" \"),\n      _c(\"br\"),\n      _vm._v(\" \"),\n      _c(\"br\"),\n      _vm._v(\" \"),\n      _c(\"br\"),\n      _vm._v(\" \"),\n      _c(\"br\"),\n      _vm._v(\" \"),\n      _c(\"br\"),\n      _vm._v(\" \"),\n      _c(\"br\"),\n      _vm._v(\" \"),\n      _c(\"br\"),\n      _vm._v(\" \"),\n      _c(\"br\"),\n      _vm._v(\" \"),\n      _c(\"br\"),\n      _vm._v(\" \"),\n      _c(\"br\"),\n      _vm._v(\" \"),\n      _c(\"br\"),\n      _vm._v(\" \"),\n      _c(\"br\"),\n      _vm._v(\" \"),\n      _c(\"br\"),\n      _vm._v(\" \"),\n      _c(\"br\"),\n      _vm._v(\" \"),\n      _c(\"br\"),\n      _vm._v(\" \"),\n      _c(\"br\"),\n      _vm._v(\" \"),\n      _c(\"br\"),\n      _vm._v(\" \"),\n      _c(\"br\"),\n      _vm._v(\" \"),\n      _c(\"br\"),\n      _vm._v(\" \"),\n      _c(\"br\"),\n      _vm._v(\" \"),\n      _c(\"br\"),\n      _vm._v(\" \"),\n      _c(\"br\"),\n      _vm._v(\" \"),\n      _c(\"br\"),\n      _vm._v(\" \"),\n      _c(\"br\"),\n      _vm._v(\" \"),\n      _c(\"br\"),\n      _vm._v(\" \"),\n      _c(\"h2\", { staticClass: \"title\" }, [_vm._v(\"alert\")]),\n      _vm._v(\" \"),\n      _c(\n        \"el-button\",\n        { attrs: { type: \"primary\" }, on: { click: _vm.submitHandle } },\n        [_vm._v(\"提交\")]\n      ),\n      _vm._v(\" \"),\n      _c(\"h2\", { staticClass: \"title\" }, [_vm._v(\"confirm\")]),\n      _vm._v(\" \"),\n      _c(\n        \"el-button\",\n        { attrs: { type: \"primary\" }, on: { click: _vm.confirmHandle } },\n        [_vm._v(\"删除\")]\n      ),\n      _vm._v(\" \"),\n      _c(\"h2\", { staticClass: \"title\" }, [_vm._v(\"msg\")]),\n      _vm._v(\" \"),\n      _c(\n        \"el-button\",\n        { attrs: { type: \"primary\" }, on: { click: _vm.msgHandle } },\n        [_vm._v(\"msg\")]\n      ),\n      _vm._v(\" \"),\n      _c(\n        \"el-button\",\n        { attrs: { type: \"primary\" }, on: { click: _vm.msg1Handle } },\n        [_vm._v(\"带回调\")]\n      ),\n      _vm._v(\" \"),\n      _c(\"h2\", { staticClass: \"title\" }, [_vm._v(\"loading\")]),\n      _vm._v(\" \"),\n      _c(\n        \"el-button\",\n        { attrs: { type: \"primary\" }, on: { click: _vm.loadingHandle } },\n        [_vm._v(\"默认样式\")]\n      ),\n      _vm._v(\" \"),\n      _c(\"h2\", { staticClass: \"title\" }, [_vm._v(\"tips\")]),\n      _vm._v(\" \"),\n      _c(\n        \"el-button\",\n        {\n          attrs: { type: \"primary\", id: \"tips\" },\n          on: { click: _vm.tipsHandle }\n        },\n        [_vm._v(\"上\")]\n      ),\n      _vm._v(\" \"),\n      _c(\n        \"el-button\",\n        {\n          attrs: { type: \"primary\", id: \"tips1\" },\n          nativeOn: {\n            mouseenter: function($event) {\n              return _vm.tips1Handle($event)\n            }\n          }\n        },\n        [_vm._v(\"右\")]\n      ),\n      _vm._v(\" \"),\n      _c(\n        \"el-button\",\n        {\n          attrs: { type: \"primary\", id: \"tips2\" },\n          on: { click: _vm.tips2Handle }\n        },\n        [_vm._v(\"下\")]\n      ),\n      _vm._v(\" \"),\n      _c(\n        \"el-button\",\n        {\n          attrs: { type: \"primary\", id: \"tips3\" },\n          on: { click: _vm.tips3Handle }\n        },\n        [_vm._v(\"左-自定义样式\")]\n      ),\n      _vm._v(\" \"),\n      _c(\"h2\", { staticClass: \"title\" }, [_vm._v(\"page\")]),\n      _vm._v(\" \"),\n      _c(\n        \"el-button\",\n        {\n          attrs: { type: \"primary\", id: \"tips\" },\n          on: { click: _vm.pageHandle }\n        },\n        [_vm._v(\"自定义\")]\n      )\n    ],\n    1\n  )\n}\nvar staticRenderFns = []\nrender._withStripped = true\n\n          return {\n            render: render,\n            staticRenderFns: staticRenderFns,\n            _compiled: true,\n            _scopeId: null,\n            functional: undefined\n          };\n        })());\n      \n    /* hot reload */\n    (function () {\n      if (module.hot) {\n        var api = require('vue-hot-reload-api');\n        api.install(require('vue'));\n        if (api.compatible) {\n          module.hot.accept();\n          if (!module.hot.data) {\n            api.createRecord('$f800f7', $f800f7);\n          } else {\n            api.reload('$f800f7', $f800f7);\n          }\n        }\n\n        \n        var reloadCSS = require('_css_loader');\n        module.hot.dispose(reloadCSS);\n        module.hot.accept(reloadCSS);\n      \n      }\n    })();","map":{"mappings":[{"source":"App.vue","name":null,"original":{"line":77,"column":0},"generated":{"line":15,"column":0}},{"source":"App.vue","name":null,"original":{"line":78,"column":0},"generated":{"line":19,"column":0}},{"source":"App.vue","name":null,"original":{"line":80,"column":0},"generated":{"line":101,"column":18}},{"source":"App.vue","name":null,"original":{"line":81,"column":0},"generated":{"line":102,"column":0}},{"source":"App.vue","name":null,"original":{"line":80,"column":0},"generated":{"line":102,"column":6}},{"source":"App.vue","name":null,"original":{"line":81,"column":0},"generated":{"line":102,"column":24}},{"source":"App.vue","name":null,"original":{"line":82,"column":0},"generated":{"line":103,"column":0}},{"source":"App.vue","name":null,"original":{"line":82,"column":0},"generated":{"line":103,"column":11}},{"source":"App.vue","name":null,"original":{"line":82,"column":0},"generated":{"line":103,"column":13}},{"source":"App.vue","name":null,"original":{"line":83,"column":0},"generated":{"line":104,"column":0}},{"source":"App.vue","name":null,"original":{"line":80,"column":0},"generated":{"line":104,"column":3}},{"source":"App.vue","name":null,"original":{"line":84,"column":0},"generated":{"line":106,"column":0}},{"source":"App.vue","name":null,"original":{"line":84,"column":0},"generated":{"line":106,"column":14}},{"source":"App.vue","name":null,"original":{"line":85,"column":0},"generated":{"line":107,"column":0}},{"source":"App.vue","name":null,"original":{"line":85,"column":0},"generated":{"line":107,"column":17}},{"source":"App.vue","name":null,"original":{"line":84,"column":0},"generated":{"line":108,"column":0}},{"source":"App.vue","name":null,"original":{"line":80,"column":0},"generated":{"line":108,"column":3}},{"source":"App.vue","name":null,"original":{"line":87,"column":0},"generated":{"line":109,"column":0}},{"source":"App.vue","name":null,"original":{"line":80,"column":0},"generated":{"line":109,"column":9}},{"source":"App.vue","name":null,"original":{"line":80,"column":0},"generated":{"line":110,"column":0}},{"source":"App.vue","name":null,"original":{"line":80,"column":0},"generated":{"line":111,"column":0}},{"source":"App.vue","name":null,"original":{"line":80,"column":0},"generated":{"line":113,"column":0}},{"source":"App.vue","name":null,"original":{"line":80,"column":0},"generated":{"line":114,"column":0}},{"source":"App.vue","name":null,"original":{"line":80,"column":0},"generated":{"line":115,"column":0}},{"source":"App.vue","name":null,"original":{"line":80,"column":0},"generated":{"line":116,"column":0}},{"source":"App.vue","name":null,"original":{"line":88,"column":0},"generated":{"line":117,"column":0}},{"source":"App.vue","name":null,"original":{"line":80,"column":0},"generated":{"line":117,"column":17}},{"source":"App.vue","name":null,"original":{"line":88,"column":0},"generated":{"line":117,"column":20}},{"source":"App.vue","name":null,"original":{"line":80,"column":0},"generated":{"line":117,"column":22}},{"source":"App.vue","name":null,"original":{"line":89,"column":0},"generated":{"line":118,"column":0}},{"source":"App.vue","name":null,"original":{"line":80,"column":0},"generated":{"line":118,"column":15}},{"source":"App.vue","name":null,"original":{"line":89,"column":0},"generated":{"line":118,"column":18}},{"source":"App.vue","name":null,"original":{"line":80,"column":0},"generated":{"line":118,"column":19}},{"source":"App.vue","name":null,"original":{"line":80,"column":0},"generated":{"line":120,"column":0}},{"source":"App.vue","name":null,"original":{"line":80,"column":0},"generated":{"line":121,"column":0}},{"source":"App.vue","name":null,"original":{"line":89,"column":0},"generated":{"line":121,"column":20}},{"source":"App.vue","name":null,"original":{"line":89,"column":0},"generated":{"line":121,"column":24}},{"source":"App.vue","name":null,"original":{"line":80,"column":0},"generated":{"line":121,"column":25}},{"source":"App.vue","name":null,"original":{"line":80,"column":0},"generated":{"line":122,"column":0}},{"source":"App.vue","name":null,"original":{"line":80,"column":0},"generated":{"line":123,"column":0}},{"source":"App.vue","name":null,"original":{"line":80,"column":0},"generated":{"line":124,"column":0}},{"source":"App.vue","name":null,"original":{"line":80,"column":0},"generated":{"line":126,"column":0}},{"source":"App.vue","name":null,"original":{"line":80,"column":0},"generated":{"line":127,"column":0}},{"source":"App.vue","name":null,"original":{"line":90,"column":0},"generated":{"line":127,"column":21}},{"source":"App.vue","name":null,"original":{"line":90,"column":0},"generated":{"line":127,"column":37}},{"source":"App.vue","name":null,"original":{"line":90,"column":0},"generated":{"line":127,"column":42}},{"source":"App.vue","name":null,"original":{"line":90,"column":0},"generated":{"line":127,"column":43}},{"source":"App.vue","name":null,"original":{"line":90,"column":0},"generated":{"line":127,"column":45}},{"source":"App.vue","name":null,"original":{"line":80,"column":0},"generated":{"line":127,"column":46}},{"source":"App.vue","name":null,"original":{"line":80,"column":0},"generated":{"line":129,"column":0}},{"source":"App.vue","name":null,"original":{"line":91,"column":0},"generated":{"line":130,"column":0}},{"source":"App.vue","name":null,"original":{"line":80,"column":0},"generated":{"line":130,"column":16}},{"source":"App.vue","name":null,"original":{"line":91,"column":0},"generated":{"line":130,"column":19}},{"source":"App.vue","name":null,"original":{"line":91,"column":0},"generated":{"line":130,"column":24}},{"source":"App.vue","name":null,"original":{"line":91,"column":0},"generated":{"line":130,"column":37}},{"source":"App.vue","name":null,"original":{"line":80,"column":0},"generated":{"line":130,"column":39}},{"source":"App.vue","name":null,"original":{"line":92,"column":0},"generated":{"line":132,"column":0}},{"source":"App.vue","name":null,"original":{"line":92,"column":0},"generated":{"line":132,"column":18}},{"source":"App.vue","name":null,"original":{"line":92,"column":0},"generated":{"line":132,"column":22}},{"source":"App.vue","name":null,"original":{"line":92,"column":0},"generated":{"line":132,"column":23}},{"source":"App.vue","name":null,"original":{"line":92,"column":0},"generated":{"line":132,"column":25}},{"source":"App.vue","name":null,"original":{"line":80,"column":0},"generated":{"line":134,"column":0}},{"source":"App.vue","name":null,"original":{"line":89,"column":0},"generated":{"line":135,"column":0}},{"source":"App.vue","name":null,"original":{"line":80,"column":0},"generated":{"line":135,"column":17}},{"source":"App.vue","name":null,"original":{"line":80,"column":0},"generated":{"line":136,"column":0}},{"source":"App.vue","name":null,"original":{"line":80,"column":0},"generated":{"line":137,"column":0}},{"source":"App.vue","name":null,"original":{"line":80,"column":0},"generated":{"line":139,"column":0}},{"source":"App.vue","name":null,"original":{"line":94,"column":0},"generated":{"line":140,"column":0}},{"source":"App.vue","name":null,"original":{"line":80,"column":0},"generated":{"line":140,"column":16}},{"source":"App.vue","name":null,"original":{"line":94,"column":0},"generated":{"line":140,"column":19}},{"source":"App.vue","name":null,"original":{"line":80,"column":0},"generated":{"line":140,"column":20}},{"source":"App.vue","name":null,"original":{"line":80,"column":0},"generated":{"line":142,"column":0}},{"source":"App.vue","name":null,"original":{"line":80,"column":0},"generated":{"line":143,"column":0}},{"source":"App.vue","name":null,"original":{"line":94,"column":0},"generated":{"line":143,"column":20}},{"source":"App.vue","name":null,"original":{"line":94,"column":0},"generated":{"line":143,"column":25}},{"source":"App.vue","name":null,"original":{"line":80,"column":0},"generated":{"line":143,"column":26}},{"source":"App.vue","name":null,"original":{"line":80,"column":0},"generated":{"line":144,"column":0}},{"source":"App.vue","name":null,"original":{"line":80,"column":0},"generated":{"line":145,"column":0}},{"source":"App.vue","name":null,"original":{"line":80,"column":0},"generated":{"line":146,"column":0}},{"source":"App.vue","name":null,"original":{"line":80,"column":0},"generated":{"line":148,"column":0}},{"source":"App.vue","name":null,"original":{"line":80,"column":0},"generated":{"line":149,"column":0}},{"source":"App.vue","name":null,"original":{"line":95,"column":0},"generated":{"line":149,"column":21}},{"source":"App.vue","name":null,"original":{"line":95,"column":0},"generated":{"line":149,"column":37}},{"source":"App.vue","name":null,"original":{"line":95,"column":0},"generated":{"line":149,"column":42}},{"source":"App.vue","name":null,"original":{"line":95,"column":0},"generated":{"line":149,"column":43}},{"source":"App.vue","name":null,"original":{"line":95,"column":0},"generated":{"line":149,"column":46}},{"source":"App.vue","name":null,"original":{"line":80,"column":0},"generated":{"line":149,"column":47}},{"source":"App.vue","name":null,"original":{"line":80,"column":0},"generated":{"line":151,"column":0}},{"source":"App.vue","name":null,"original":{"line":96,"column":0},"generated":{"line":152,"column":0}},{"source":"App.vue","name":null,"original":{"line":96,"column":0},"generated":{"line":152,"column":19}},{"source":"App.vue","name":null,"original":{"line":96,"column":0},"generated":{"line":152,"column":25}},{"source":"App.vue","name":null,"original":{"line":96,"column":0},"generated":{"line":152,"column":26}},{"source":"App.vue","name":null,"original":{"line":96,"column":0},"generated":{"line":152,"column":31}},{"source":"App.vue","name":null,"original":{"line":96,"column":0},"generated":{"line":152,"column":32}},{"source":"App.vue","name":null,"original":{"line":96,"column":0},"generated":{"line":152,"column":36}},{"source":"App.vue","name":null,"original":{"line":96,"column":0},"generated":{"line":152,"column":38}},{"source":"App.vue","name":null,"original":{"line":96,"column":0},"generated":{"line":152,"column":39}},{"source":"App.vue","name":null,"original":{"line":80,"column":0},"generated":{"line":154,"column":0}},{"source":"App.vue","name":null,"original":{"line":94,"column":0},"generated":{"line":155,"column":0}},{"source":"App.vue","name":null,"original":{"line":80,"column":0},"generated":{"line":155,"column":18}},{"source":"App.vue","name":null,"original":{"line":80,"column":0},"generated":{"line":156,"column":0}},{"source":"App.vue","name":null,"original":{"line":80,"column":0},"generated":{"line":157,"column":0}},{"source":"App.vue","name":null,"original":{"line":80,"column":0},"generated":{"line":159,"column":0}},{"source":"App.vue","name":null,"original":{"line":98,"column":0},"generated":{"line":160,"column":0}},{"source":"App.vue","name":null,"original":{"line":98,"column":0},"generated":{"line":160,"column":19}},{"source":"App.vue","name":null,"original":{"line":98,"column":0},"generated":{"line":160,"column":22}},{"source":"App.vue","name":null,"original":{"line":98,"column":0},"generated":{"line":160,"column":23}},{"source":"App.vue","name":null,"original":{"line":98,"column":0},"generated":{"line":160,"column":28}},{"source":"App.vue","name":null,"original":{"line":98,"column":0},"generated":{"line":160,"column":30}},{"source":"App.vue","name":null,"original":{"line":98,"column":0},"generated":{"line":160,"column":40}},{"source":"App.vue","name":null,"original":{"line":98,"column":0},"generated":{"line":160,"column":43}},{"source":"App.vue","name":null,"original":{"line":98,"column":0},"generated":{"line":160,"column":45}},{"source":"App.vue","name":null,"original":{"line":99,"column":0},"generated":{"line":161,"column":0}},{"source":"App.vue","name":null,"original":{"line":99,"column":0},"generated":{"line":161,"column":21}},{"source":"App.vue","name":null,"original":{"line":99,"column":0},"generated":{"line":161,"column":27}},{"source":"App.vue","name":null,"original":{"line":99,"column":0},"generated":{"line":161,"column":28}},{"source":"App.vue","name":null,"original":{"line":99,"column":0},"generated":{"line":161,"column":31}},{"source":"App.vue","name":null,"original":{"line":99,"column":0},"generated":{"line":161,"column":32}},{"source":"App.vue","name":null,"original":{"line":99,"column":0},"generated":{"line":161,"column":35}},{"source":"App.vue","name":null,"original":{"line":100,"column":0},"generated":{"line":162,"column":0}},{"source":"App.vue","name":null,"original":{"line":98,"column":0},"generated":{"line":162,"column":15}},{"source":"App.vue","name":null,"original":{"line":80,"column":0},"generated":{"line":164,"column":0}},{"source":"App.vue","name":null,"original":{"line":80,"column":0},"generated":{"line":165,"column":0}},{"source":"App.vue","name":null,"original":{"line":80,"column":0},"generated":{"line":166,"column":0}},{"source":"App.vue","name":null,"original":{"line":80,"column":0},"generated":{"line":167,"column":0}},{"source":"App.vue","name":null,"original":{"line":80,"column":0},"generated":{"line":168,"column":0}},{"source":"App.vue","name":null,"original":{"line":80,"column":0},"generated":{"line":169,"column":0}},{"source":"App.vue","name":null,"original":{"line":80,"column":0},"generated":{"line":170,"column":0}},{"source":"App.vue","name":null,"original":{"line":80,"column":0},"generated":{"line":172,"column":0}},{"source":"App.vue","name":null,"original":{"line":80,"column":0},"generated":{"line":173,"column":0}},{"source":"App.vue","name":null,"original":{"line":80,"column":0},"generated":{"line":174,"column":0}},{"source":"App.vue","name":null,"original":{"line":80,"column":0},"generated":{"line":176,"column":0}},{"source":"App.vue","name":null,"original":{"line":80,"column":0},"generated":{"line":177,"column":0}},{"source":"App.vue","name":null,"original":{"line":102,"column":0},"generated":{"line":179,"column":0}},{"source":"App.vue","name":null,"original":{"line":102,"column":0},"generated":{"line":179,"column":11}},{"source":"App.vue","name":null,"original":{"line":103,"column":0},"generated":{"line":180,"column":0}},{"source":"App.vue","name":null,"original":{"line":103,"column":0},"generated":{"line":180,"column":18}},{"source":"App.vue","name":null,"original":{"line":103,"column":0},"generated":{"line":180,"column":42}},{"source":"App.vue","name":null,"original":{"line":103,"column":0},"generated":{"line":181,"column":0}},{"source":"App.vue","name":null,"original":{"line":104,"column":0},"generated":{"line":183,"column":0}},{"source":"App.vue","name":null,"original":{"line":104,"column":0},"generated":{"line":183,"column":10}},{"source":"App.vue","name":null,"original":{"line":104,"column":0},"generated":{"line":183,"column":15}},{"source":"App.vue","name":null,"original":{"line":104,"column":0},"generated":{"line":183,"column":20}},{"source":"App.vue","name":null,"original":{"line":104,"column":0},"generated":{"line":183,"column":26}},{"source":"App.vue","name":null,"original":{"line":104,"column":0},"generated":{"line":183,"column":27}},{"source":"App.vue","name":null,"original":{"line":104,"column":0},"generated":{"line":183,"column":32}},{"source":"App.vue","name":null,"original":{"line":105,"column":0},"generated":{"line":183,"column":33}},{"source":"App.vue","name":null,"original":{"line":104,"column":0},"generated":{"line":183,"column":310}},{"source":"App.vue","name":null,"original":{"line":106,"column":0},"generated":{"line":183,"column":312}},{"source":"App.vue","name":null,"original":{"line":107,"column":0},"generated":{"line":184,"column":0}},{"source":"App.vue","name":null,"original":{"line":107,"column":0},"generated":{"line":184,"column":15}},{"source":"App.vue","name":null,"original":{"line":106,"column":0},"generated":{"line":185,"column":0}},{"source":"App.vue","name":null,"original":{"line":104,"column":0},"generated":{"line":185,"column":7}},{"source":"App.vue","name":null,"original":{"line":109,"column":0},"generated":{"line":185,"column":9}},{"source":"App.vue","name":null,"original":{"line":109,"column":0},"generated":{"line":185,"column":21}},{"source":"App.vue","name":null,"original":{"line":110,"column":0},"generated":{"line":186,"column":0}},{"source":"App.vue","name":null,"original":{"line":110,"column":0},"generated":{"line":186,"column":14}},{"source":"App.vue","name":null,"original":{"line":110,"column":0},"generated":{"line":186,"column":15}},{"source":"App.vue","name":null,"original":{"line":111,"column":0},"generated":{"line":187,"column":0}},{"source":"App.vue","name":null,"original":{"line":111,"column":0},"generated":{"line":187,"column":14}},{"source":"App.vue","name":null,"original":{"line":111,"column":0},"generated":{"line":187,"column":20}},{"source":"App.vue","name":null,"original":{"line":111,"column":0},"generated":{"line":187,"column":21}},{"source":"App.vue","name":null,"original":{"line":111,"column":0},"generated":{"line":187,"column":26}},{"source":"App.vue","name":null,"original":{"line":111,"column":0},"generated":{"line":187,"column":27}},{"source":"App.vue","name":null,"original":{"line":111,"column":0},"generated":{"line":187,"column":29}},{"source":"App.vue","name":null,"original":{"line":112,"column":0},"generated":{"line":188,"column":0}},{"source":"App.vue","name":null,"original":{"line":104,"column":0},"generated":{"line":188,"column":7}},{"source":"App.vue","name":null,"original":{"line":104,"column":0},"generated":{"line":188,"column":8}},{"source":"App.vue","name":null,"original":{"line":114,"column":0},"generated":{"line":189,"column":0}},{"source":"App.vue","name":null,"original":{"line":102,"column":0},"generated":{"line":189,"column":5}},{"source":"App.vue","name":null,"original":{"line":115,"column":0},"generated":{"line":190,"column":0}},{"source":"App.vue","name":null,"original":{"line":115,"column":0},"generated":{"line":190,"column":19}},{"source":"App.vue","name":null,"original":{"line":115,"column":0},"generated":{"line":190,"column":44}},{"source":"App.vue","name":null,"original":{"line":115,"column":0},"generated":{"line":191,"column":0}},{"source":"App.vue","name":null,"original":{"line":116,"column":0},"generated":{"line":193,"column":0}},{"source":"App.vue","name":null,"original":{"line":116,"column":0},"generated":{"line":193,"column":10}},{"source":"App.vue","name":null,"original":{"line":116,"column":0},"generated":{"line":193,"column":15}},{"source":"App.vue","name":null,"original":{"line":116,"column":0},"generated":{"line":193,"column":20}},{"source":"App.vue","name":null,"original":{"line":116,"column":0},"generated":{"line":193,"column":26}},{"source":"App.vue","name":null,"original":{"line":116,"column":0},"generated":{"line":193,"column":27}},{"source":"App.vue","name":null,"original":{"line":116,"column":0},"generated":{"line":193,"column":34}},{"source":"App.vue","name":null,"original":{"line":117,"column":0},"generated":{"line":193,"column":35}},{"source":"App.vue","name":null,"original":{"line":116,"column":0},"generated":{"line":193,"column":49}},{"source":"App.vue","name":null,"original":{"line":118,"column":0},"generated":{"line":193,"column":51}},{"source":"App.vue","name":null,"original":{"line":118,"column":0},"generated":{"line":193,"column":63}},{"source":"App.vue","name":null,"original":{"line":119,"column":0},"generated":{"line":194,"column":0}},{"source":"App.vue","name":null,"original":{"line":119,"column":0},"generated":{"line":194,"column":15}},{"source":"App.vue","name":null,"original":{"line":119,"column":0},"generated":{"line":194,"column":21}},{"source":"App.vue","name":null,"original":{"line":119,"column":0},"generated":{"line":194,"column":22}},{"source":"App.vue","name":null,"original":{"line":119,"column":0},"generated":{"line":194,"column":25}},{"source":"App.vue","name":null,"original":{"line":119,"column":0},"generated":{"line":194,"column":26}},{"source":"App.vue","name":null,"original":{"line":119,"column":0},"generated":{"line":194,"column":33}},{"source":"App.vue","name":null,"original":{"line":120,"column":0},"generated":{"line":195,"column":0}},{"source":"App.vue","name":null,"original":{"line":120,"column":0},"generated":{"line":195,"column":15}},{"source":"App.vue","name":null,"original":{"line":120,"column":0},"generated":{"line":195,"column":21}},{"source":"App.vue","name":null,"original":{"line":120,"column":0},"generated":{"line":195,"column":22}},{"source":"App.vue","name":null,"original":{"line":120,"column":0},"generated":{"line":195,"column":27}},{"source":"App.vue","name":null,"original":{"line":120,"column":0},"generated":{"line":195,"column":28}},{"source":"App.vue","name":null,"original":{"line":120,"column":0},"generated":{"line":195,"column":30}},{"source":"App.vue","name":null,"original":{"line":121,"column":0},"generated":{"line":196,"column":0}},{"source":"App.vue","name":null,"original":{"line":116,"column":0},"generated":{"line":196,"column":7}},{"source":"App.vue","name":null,"original":{"line":122,"column":0},"generated":{"line":196,"column":9}},{"source":"App.vue","name":null,"original":{"line":122,"column":0},"generated":{"line":196,"column":21}},{"source":"App.vue","name":null,"original":{"line":123,"column":0},"generated":{"line":197,"column":0}},{"source":"App.vue","name":null,"original":{"line":123,"column":0},"generated":{"line":197,"column":15}},{"source":"App.vue","name":null,"original":{"line":123,"column":0},"generated":{"line":197,"column":21}},{"source":"App.vue","name":null,"original":{"line":123,"column":0},"generated":{"line":197,"column":22}},{"source":"App.vue","name":null,"original":{"line":123,"column":0},"generated":{"line":197,"column":25}},{"source":"App.vue","name":null,"original":{"line":123,"column":0},"generated":{"line":197,"column":26}},{"source":"App.vue","name":null,"original":{"line":123,"column":0},"generated":{"line":197,"column":32}},{"source":"App.vue","name":null,"original":{"line":124,"column":0},"generated":{"line":198,"column":0}},{"source":"App.vue","name":null,"original":{"line":124,"column":0},"generated":{"line":198,"column":15}},{"source":"App.vue","name":null,"original":{"line":124,"column":0},"generated":{"line":198,"column":21}},{"source":"App.vue","name":null,"original":{"line":124,"column":0},"generated":{"line":198,"column":22}},{"source":"App.vue","name":null,"original":{"line":124,"column":0},"generated":{"line":198,"column":27}},{"source":"App.vue","name":null,"original":{"line":124,"column":0},"generated":{"line":198,"column":28}},{"source":"App.vue","name":null,"original":{"line":124,"column":0},"generated":{"line":198,"column":30}},{"source":"App.vue","name":null,"original":{"line":125,"column":0},"generated":{"line":199,"column":0}},{"source":"App.vue","name":null,"original":{"line":116,"column":0},"generated":{"line":199,"column":7}},{"source":"App.vue","name":null,"original":{"line":116,"column":0},"generated":{"line":199,"column":8}},{"source":"App.vue","name":null,"original":{"line":127,"column":0},"generated":{"line":200,"column":0}},{"source":"App.vue","name":null,"original":{"line":102,"column":0},"generated":{"line":200,"column":5}},{"source":"App.vue","name":null,"original":{"line":128,"column":0},"generated":{"line":201,"column":0}},{"source":"App.vue","name":null,"original":{"line":128,"column":0},"generated":{"line":201,"column":15}},{"source":"App.vue","name":null,"original":{"line":128,"column":0},"generated":{"line":201,"column":36}},{"source":"App.vue","name":null,"original":{"line":129,"column":0},"generated":{"line":202,"column":0}},{"source":"App.vue","name":null,"original":{"line":129,"column":0},"generated":{"line":202,"column":10}},{"source":"App.vue","name":null,"original":{"line":129,"column":0},"generated":{"line":202,"column":15}},{"source":"App.vue","name":null,"original":{"line":129,"column":0},"generated":{"line":202,"column":20}},{"source":"App.vue","name":null,"original":{"line":129,"column":0},"generated":{"line":202,"column":26}},{"source":"App.vue","name":null,"original":{"line":129,"column":0},"generated":{"line":202,"column":27}},{"source":"App.vue","name":null,"original":{"line":129,"column":0},"generated":{"line":202,"column":30}},{"source":"App.vue","name":null,"original":{"line":129,"column":0},"generated":{"line":202,"column":31}},{"source":"App.vue","name":null,"original":{"line":129,"column":0},"generated":{"line":202,"column":38}},{"source":"App.vue","name":null,"original":{"line":129,"column":0},"generated":{"line":202,"column":39}},{"source":"App.vue","name":null,"original":{"line":130,"column":0},"generated":{"line":203,"column":0}},{"source":"App.vue","name":null,"original":{"line":102,"column":0},"generated":{"line":203,"column":5}},{"source":"App.vue","name":null,"original":{"line":131,"column":0},"generated":{"line":204,"column":0}},{"source":"App.vue","name":null,"original":{"line":131,"column":0},"generated":{"line":204,"column":16}},{"source":"App.vue","name":null,"original":{"line":131,"column":0},"generated":{"line":204,"column":38}},{"source":"App.vue","name":null,"original":{"line":131,"column":0},"generated":{"line":205,"column":0}},{"source":"App.vue","name":null,"original":{"line":132,"column":0},"generated":{"line":207,"column":0}},{"source":"App.vue","name":null,"original":{"line":132,"column":0},"generated":{"line":207,"column":10}},{"source":"App.vue","name":null,"original":{"line":132,"column":0},"generated":{"line":207,"column":15}},{"source":"App.vue","name":null,"original":{"line":132,"column":0},"generated":{"line":207,"column":20}},{"source":"App.vue","name":null,"original":{"line":132,"column":0},"generated":{"line":207,"column":26}},{"source":"App.vue","name":null,"original":{"line":132,"column":0},"generated":{"line":207,"column":27}},{"source":"App.vue","name":null,"original":{"line":132,"column":0},"generated":{"line":207,"column":30}},{"source":"App.vue","name":null,"original":{"line":133,"column":0},"generated":{"line":207,"column":31}},{"source":"App.vue","name":null,"original":{"line":132,"column":0},"generated":{"line":207,"column":40}},{"source":"App.vue","name":null,"original":{"line":134,"column":0},"generated":{"line":207,"column":42}},{"source":"App.vue","name":null,"original":{"line":135,"column":0},"generated":{"line":208,"column":0}},{"source":"App.vue","name":null,"original":{"line":135,"column":0},"generated":{"line":208,"column":14}},{"source":"App.vue","name":null,"original":{"line":134,"column":0},"generated":{"line":209,"column":0}},{"source":"App.vue","name":null,"original":{"line":132,"column":0},"generated":{"line":209,"column":7}},{"source":"App.vue","name":null,"original":{"line":137,"column":0},"generated":{"line":209,"column":9}},{"source":"App.vue","name":null,"original":{"line":137,"column":0},"generated":{"line":209,"column":21}},{"source":"App.vue","name":null,"original":{"line":138,"column":0},"generated":{"line":210,"column":0}},{"source":"App.vue","name":null,"original":{"line":138,"column":0},"generated":{"line":210,"column":15}},{"source":"App.vue","name":null,"original":{"line":138,"column":0},"generated":{"line":210,"column":21}},{"source":"App.vue","name":null,"original":{"line":138,"column":0},"generated":{"line":210,"column":22}},{"source":"App.vue","name":null,"original":{"line":138,"column":0},"generated":{"line":210,"column":27}},{"source":"App.vue","name":null,"original":{"line":138,"column":0},"generated":{"line":210,"column":28}},{"source":"App.vue","name":null,"original":{"line":138,"column":0},"generated":{"line":210,"column":30}},{"source":"App.vue","name":null,"original":{"line":139,"column":0},"generated":{"line":211,"column":0}},{"source":"App.vue","name":null,"original":{"line":132,"column":0},"generated":{"line":211,"column":7}},{"source":"App.vue","name":null,"original":{"line":132,"column":0},"generated":{"line":211,"column":8}},{"source":"App.vue","name":null,"original":{"line":141,"column":0},"generated":{"line":212,"column":0}},{"source":"App.vue","name":null,"original":{"line":102,"column":0},"generated":{"line":212,"column":5}},{"source":"App.vue","name":null,"original":{"line":142,"column":0},"generated":{"line":213,"column":0}},{"source":"App.vue","name":null,"original":{"line":142,"column":0},"generated":{"line":213,"column":19}},{"source":"App.vue","name":null,"original":{"line":142,"column":0},"generated":{"line":213,"column":44}},{"source":"App.vue","name":null,"original":{"line":143,"column":0},"generated":{"line":214,"column":0}},{"source":"App.vue","name":null,"original":{"line":143,"column":0},"generated":{"line":214,"column":10}},{"source":"App.vue","name":null,"original":{"line":143,"column":0},"generated":{"line":214,"column":15}},{"source":"App.vue","name":null,"original":{"line":143,"column":0},"generated":{"line":214,"column":20}},{"source":"App.vue","name":null,"original":{"line":143,"column":0},"generated":{"line":214,"column":26}},{"source":"App.vue","name":null,"original":{"line":143,"column":0},"generated":{"line":214,"column":27}},{"source":"App.vue","name":null,"original":{"line":143,"column":0},"generated":{"line":214,"column":34}},{"source":"App.vue","name":null,"original":{"line":143,"column":0},"generated":{"line":214,"column":35}},{"source":"App.vue","name":null,"original":{"line":144,"column":0},"generated":{"line":215,"column":0}},{"source":"App.vue","name":null,"original":{"line":144,"column":0},"generated":{"line":215,"column":14}},{"source":"App.vue","name":null,"original":{"line":143,"column":0},"generated":{"line":216,"column":0}},{"source":"App.vue","name":null,"original":{"line":143,"column":0},"generated":{"line":216,"column":7}},{"source":"App.vue","name":null,"original":{"line":143,"column":0},"generated":{"line":216,"column":8}},{"source":"App.vue","name":null,"original":{"line":146,"column":0},"generated":{"line":217,"column":0}},{"source":"App.vue","name":null,"original":{"line":146,"column":0},"generated":{"line":217,"column":13}},{"source":"App.vue","name":null,"original":{"line":146,"column":0},"generated":{"line":217,"column":15}},{"source":"App.vue","name":null,"original":{"line":147,"column":0},"generated":{"line":218,"column":0}},{"source":"App.vue","name":null,"original":{"line":102,"column":0},"generated":{"line":218,"column":5}},{"source":"App.vue","name":null,"original":{"line":148,"column":0},"generated":{"line":219,"column":0}},{"source":"App.vue","name":null,"original":{"line":148,"column":0},"generated":{"line":219,"column":16}},{"source":"App.vue","name":null,"original":{"line":148,"column":0},"generated":{"line":219,"column":38}},{"source":"App.vue","name":null,"original":{"line":149,"column":0},"generated":{"line":220,"column":0}},{"source":"App.vue","name":null,"original":{"line":149,"column":0},"generated":{"line":220,"column":10}},{"source":"App.vue","name":null,"original":{"line":149,"column":0},"generated":{"line":220,"column":15}},{"source":"App.vue","name":null,"original":{"line":149,"column":0},"generated":{"line":220,"column":20}},{"source":"App.vue","name":null,"original":{"line":149,"column":0},"generated":{"line":220,"column":26}},{"source":"App.vue","name":null,"original":{"line":149,"column":0},"generated":{"line":220,"column":27}},{"source":"App.vue","name":null,"original":{"line":149,"column":0},"generated":{"line":220,"column":31}},{"source":"App.vue","name":null,"original":{"line":149,"column":0},"generated":{"line":220,"column":32}},{"source":"App.vue","name":null,"original":{"line":149,"column":0},"generated":{"line":220,"column":41}},{"source":"App.vue","name":null,"original":{"line":149,"column":0},"generated":{"line":220,"column":43}},{"source":"App.vue","name":null,"original":{"line":149,"column":0},"generated":{"line":220,"column":50}},{"source":"App.vue","name":null,"original":{"line":149,"column":0},"generated":{"line":220,"column":52}},{"source":"App.vue","name":null,"original":{"line":150,"column":0},"generated":{"line":221,"column":0}},{"source":"App.vue","name":null,"original":{"line":150,"column":0},"generated":{"line":221,"column":14}},{"source":"App.vue","name":null,"original":{"line":149,"column":0},"generated":{"line":221,"column":15}},{"source":"App.vue","name":null,"original":{"line":151,"column":0},"generated":{"line":222,"column":0}},{"source":"App.vue","name":null,"original":{"line":151,"column":0},"generated":{"line":222,"column":14}},{"source":"App.vue","name":null,"original":{"line":149,"column":0},"generated":{"line":223,"column":0}},{"source":"App.vue","name":null,"original":{"line":149,"column":0},"generated":{"line":223,"column":7}},{"source":"App.vue","name":null,"original":{"line":149,"column":0},"generated":{"line":223,"column":8}},{"source":"App.vue","name":null,"original":{"line":153,"column":0},"generated":{"line":224,"column":0}},{"source":"App.vue","name":null,"original":{"line":102,"column":0},"generated":{"line":224,"column":5}},{"source":"App.vue","name":null,"original":{"line":154,"column":0},"generated":{"line":225,"column":0}},{"source":"App.vue","name":null,"original":{"line":154,"column":0},"generated":{"line":225,"column":17}},{"source":"App.vue","name":null,"original":{"line":154,"column":0},"generated":{"line":225,"column":40}},{"source":"App.vue","name":null,"original":{"line":155,"column":0},"generated":{"line":226,"column":0}},{"source":"App.vue","name":null,"original":{"line":155,"column":0},"generated":{"line":226,"column":10}},{"source":"App.vue","name":null,"original":{"line":155,"column":0},"generated":{"line":226,"column":15}},{"source":"App.vue","name":null,"original":{"line":155,"column":0},"generated":{"line":226,"column":20}},{"source":"App.vue","name":null,"original":{"line":155,"column":0},"generated":{"line":226,"column":26}},{"source":"App.vue","name":null,"original":{"line":155,"column":0},"generated":{"line":226,"column":27}},{"source":"App.vue","name":null,"original":{"line":155,"column":0},"generated":{"line":226,"column":31}},{"source":"App.vue","name":null,"original":{"line":156,"column":0},"generated":{"line":226,"column":32}},{"source":"App.vue","name":null,"original":{"line":155,"column":0},"generated":{"line":226,"column":82}},{"source":"App.vue","name":null,"original":{"line":157,"column":0},"generated":{"line":226,"column":84}},{"source":"App.vue","name":null,"original":{"line":155,"column":0},"generated":{"line":226,"column":92}},{"source":"App.vue","name":null,"original":{"line":158,"column":0},"generated":{"line":226,"column":94}},{"source":"App.vue","name":null,"original":{"line":159,"column":0},"generated":{"line":227,"column":0}},{"source":"App.vue","name":null,"original":{"line":159,"column":0},"generated":{"line":227,"column":14}},{"source":"App.vue","name":null,"original":{"line":158,"column":0},"generated":{"line":227,"column":15}},{"source":"App.vue","name":null,"original":{"line":160,"column":0},"generated":{"line":228,"column":0}},{"source":"App.vue","name":null,"original":{"line":160,"column":0},"generated":{"line":228,"column":14}},{"source":"App.vue","name":null,"original":{"line":158,"column":0},"generated":{"line":229,"column":0}},{"source":"App.vue","name":null,"original":{"line":155,"column":0},"generated":{"line":229,"column":7}},{"source":"App.vue","name":null,"original":{"line":155,"column":0},"generated":{"line":229,"column":8}},{"source":"App.vue","name":null,"original":{"line":163,"column":0},"generated":{"line":230,"column":0}},{"source":"App.vue","name":null,"original":{"line":102,"column":0},"generated":{"line":230,"column":5}},{"source":"App.vue","name":null,"original":{"line":164,"column":0},"generated":{"line":231,"column":0}},{"source":"App.vue","name":null,"original":{"line":164,"column":0},"generated":{"line":231,"column":17}},{"source":"App.vue","name":null,"original":{"line":164,"column":0},"generated":{"line":231,"column":40}},{"source":"App.vue","name":null,"original":{"line":165,"column":0},"generated":{"line":232,"column":0}},{"source":"App.vue","name":null,"original":{"line":165,"column":0},"generated":{"line":232,"column":10}},{"source":"App.vue","name":null,"original":{"line":165,"column":0},"generated":{"line":232,"column":15}},{"source":"App.vue","name":null,"original":{"line":165,"column":0},"generated":{"line":232,"column":20}},{"source":"App.vue","name":null,"original":{"line":165,"column":0},"generated":{"line":232,"column":26}},{"source":"App.vue","name":null,"original":{"line":165,"column":0},"generated":{"line":232,"column":27}},{"source":"App.vue","name":null,"original":{"line":165,"column":0},"generated":{"line":232,"column":31}},{"source":"App.vue","name":null,"original":{"line":166,"column":0},"generated":{"line":232,"column":32}},{"source":"App.vue","name":null,"original":{"line":165,"column":0},"generated":{"line":232,"column":82}},{"source":"App.vue","name":null,"original":{"line":167,"column":0},"generated":{"line":232,"column":84}},{"source":"App.vue","name":null,"original":{"line":165,"column":0},"generated":{"line":232,"column":92}},{"source":"App.vue","name":null,"original":{"line":168,"column":0},"generated":{"line":232,"column":94}},{"source":"App.vue","name":null,"original":{"line":169,"column":0},"generated":{"line":233,"column":0}},{"source":"App.vue","name":null,"original":{"line":169,"column":0},"generated":{"line":233,"column":14}},{"source":"App.vue","name":null,"original":{"line":168,"column":0},"generated":{"line":234,"column":0}},{"source":"App.vue","name":null,"original":{"line":165,"column":0},"generated":{"line":234,"column":7}},{"source":"App.vue","name":null,"original":{"line":165,"column":0},"generated":{"line":234,"column":8}},{"source":"App.vue","name":null,"original":{"line":172,"column":0},"generated":{"line":235,"column":0}},{"source":"App.vue","name":null,"original":{"line":102,"column":0},"generated":{"line":235,"column":5}},{"source":"App.vue","name":null,"original":{"line":173,"column":0},"generated":{"line":236,"column":0}},{"source":"App.vue","name":null,"original":{"line":173,"column":0},"generated":{"line":236,"column":17}},{"source":"App.vue","name":null,"original":{"line":173,"column":0},"generated":{"line":236,"column":40}},{"source":"App.vue","name":null,"original":{"line":174,"column":0},"generated":{"line":237,"column":0}},{"source":"App.vue","name":null,"original":{"line":174,"column":0},"generated":{"line":237,"column":10}},{"source":"App.vue","name":null,"original":{"line":174,"column":0},"generated":{"line":237,"column":15}},{"source":"App.vue","name":null,"original":{"line":174,"column":0},"generated":{"line":237,"column":20}},{"source":"App.vue","name":null,"original":{"line":174,"column":0},"generated":{"line":237,"column":26}},{"source":"App.vue","name":null,"original":{"line":174,"column":0},"generated":{"line":237,"column":27}},{"source":"App.vue","name":null,"original":{"line":174,"column":0},"generated":{"line":237,"column":31}},{"source":"App.vue","name":null,"original":{"line":175,"column":0},"generated":{"line":237,"column":32}},{"source":"App.vue","name":null,"original":{"line":174,"column":0},"generated":{"line":237,"column":82}},{"source":"App.vue","name":null,"original":{"line":176,"column":0},"generated":{"line":237,"column":84}},{"source":"App.vue","name":null,"original":{"line":174,"column":0},"generated":{"line":237,"column":92}},{"source":"App.vue","name":null,"original":{"line":177,"column":0},"generated":{"line":237,"column":94}},{"source":"App.vue","name":null,"original":{"line":178,"column":0},"generated":{"line":238,"column":0}},{"source":"App.vue","name":null,"original":{"line":178,"column":0},"generated":{"line":238,"column":14}},{"source":"App.vue","name":null,"original":{"line":179,"column":0},"generated":{"line":238,"column":15}},{"source":"App.vue","name":null,"original":{"line":178,"column":0},"generated":{"line":238,"column":16}},{"source":"App.vue","name":null,"original":{"line":180,"column":0},"generated":{"line":238,"column":18}},{"source":"App.vue","name":null,"original":{"line":181,"column":0},"generated":{"line":239,"column":0}},{"source":"App.vue","name":null,"original":{"line":181,"column":0},"generated":{"line":239,"column":17}},{"source":"App.vue","name":null,"original":{"line":180,"column":0},"generated":{"line":240,"column":0}},{"source":"App.vue","name":null,"original":{"line":178,"column":0},"generated":{"line":240,"column":9}},{"source":"App.vue","name":null,"original":{"line":177,"column":0},"generated":{"line":240,"column":10}},{"source":"App.vue","name":null,"original":{"line":184,"column":0},"generated":{"line":241,"column":0}},{"source":"App.vue","name":null,"original":{"line":184,"column":0},"generated":{"line":241,"column":14}},{"source":"App.vue","name":null,"original":{"line":177,"column":0},"generated":{"line":242,"column":0}},{"source":"App.vue","name":null,"original":{"line":174,"column":0},"generated":{"line":242,"column":7}},{"source":"App.vue","name":null,"original":{"line":174,"column":0},"generated":{"line":242,"column":8}},{"source":"App.vue","name":null,"original":{"line":187,"column":0},"generated":{"line":243,"column":0}},{"source":"App.vue","name":null,"original":{"line":102,"column":0},"generated":{"line":243,"column":5}},{"source":"App.vue","name":null,"original":{"line":188,"column":0},"generated":{"line":244,"column":0}},{"source":"App.vue","name":null,"original":{"line":188,"column":0},"generated":{"line":244,"column":16}},{"source":"App.vue","name":null,"original":{"line":188,"column":0},"generated":{"line":244,"column":38}},{"source":"App.vue","name":null,"original":{"line":189,"column":0},"generated":{"line":245,"column":0}},{"source":"App.vue","name":null,"original":{"line":189,"column":0},"generated":{"line":245,"column":10}},{"source":"App.vue","name":null,"original":{"line":189,"column":0},"generated":{"line":245,"column":16}},{"source":"App.vue","name":null,"original":{"line":189,"column":0},"generated":{"line":245,"column":21}},{"source":"App.vue","name":null,"original":{"line":189,"column":0},"generated":{"line":245,"column":27}},{"source":"App.vue","name":null,"original":{"line":189,"column":0},"generated":{"line":245,"column":28}},{"source":"App.vue","name":null,"original":{"line":189,"column":0},"generated":{"line":245,"column":34}},{"source":"App.vue","name":null,"original":{"line":189,"column":0},"generated":{"line":245,"column":35}},{"source":"App.vue","name":null,"original":{"line":190,"column":0},"generated":{"line":246,"column":0}},{"source":"App.vue","name":null,"original":{"line":190,"column":0},"generated":{"line":246,"column":17}},{"source":"App.vue","name":null,"original":{"line":191,"column":0},"generated":{"line":247,"column":0}},{"source":"App.vue","name":null,"original":{"line":191,"column":0},"generated":{"line":247,"column":19}},{"source":"App.vue","name":null,"original":{"line":190,"column":0},"generated":{"line":247,"column":33}},{"source":"App.vue","name":null,"original":{"line":192,"column":0},"generated":{"line":248,"column":0}},{"source":"App.vue","name":null,"original":{"line":192,"column":0},"generated":{"line":248,"column":18}},{"source":"App.vue","name":null,"original":{"line":190,"column":0},"generated":{"line":248,"column":22}},{"source":"App.vue","name":null,"original":{"line":193,"column":0},"generated":{"line":249,"column":0}},{"source":"App.vue","name":null,"original":{"line":193,"column":0},"generated":{"line":249,"column":16}},{"source":"App.vue","name":null,"original":{"line":194,"column":0},"generated":{"line":250,"column":0}},{"source":"App.vue","name":null,"original":{"line":194,"column":0},"generated":{"line":250,"column":19}},{"source":"App.vue","name":null,"original":{"line":193,"column":0},"generated":{"line":251,"column":0}},{"source":"App.vue","name":null,"original":{"line":190,"column":0},"generated":{"line":252,"column":0}},{"source":"App.vue","name":null,"original":{"line":189,"column":0},"generated":{"line":252,"column":9}},{"source":"App.vue","name":null,"original":{"line":197,"column":0},"generated":{"line":253,"column":0}},{"source":"App.vue","name":null,"original":{"line":197,"column":0},"generated":{"line":253,"column":14}},{"source":"App.vue","name":null,"original":{"line":197,"column":0},"generated":{"line":253,"column":15}},{"source":"App.vue","name":null,"original":{"line":197,"column":0},"generated":{"line":253,"column":22}},{"source":"App.vue","name":null,"original":{"line":197,"column":0},"generated":{"line":253,"column":24}},{"source":"App.vue","name":null,"original":{"line":197,"column":0},"generated":{"line":253,"column":31}},{"source":"App.vue","name":null,"original":{"line":189,"column":0},"generated":{"line":253,"column":32}},{"source":"App.vue","name":null,"original":{"line":198,"column":0},"generated":{"line":254,"column":0}},{"source":"App.vue","name":null,"original":{"line":198,"column":0},"generated":{"line":254,"column":15}},{"source":"App.vue","name":null,"original":{"line":189,"column":0},"generated":{"line":254,"column":17}},{"source":"App.vue","name":null,"original":{"line":199,"column":0},"generated":{"line":255,"column":0}},{"source":"App.vue","name":null,"original":{"line":199,"column":0},"generated":{"line":255,"column":15}},{"source":"App.vue","name":null,"original":{"line":189,"column":0},"generated":{"line":256,"column":0}},{"source":"App.vue","name":null,"original":{"line":189,"column":0},"generated":{"line":256,"column":7}},{"source":"App.vue","name":null,"original":{"line":189,"column":0},"generated":{"line":256,"column":8}},{"source":"App.vue","name":null,"original":{"line":201,"column":0},"generated":{"line":257,"column":0}},{"source":"App.vue","name":null,"original":{"line":102,"column":0},"generated":{"line":258,"column":0}},{"source":"App.vue","name":null,"original":{"line":80,"column":0},"generated":{"line":259,"column":0}}],"sources":{"App.vue":"<!--\r\n@Author: 左盐\r\n@Date:   2018-03-05 16:18:21\r\n@Email:  huabinglan@163.com\r\n@Last modified by:   左盐\r\n@Last modified time: 2018-03-31 10:10:13\r\n-->\r\n\r\n\r\n\r\n<style lang=\"less\">\r\n.title {\r\n  height: 30px;\r\n  line-height: 30px;\r\n  margin-top: 30px;\r\n  margin-bottom: 10px;\r\n}\r\n</style>\r\n<template>\r\n<div id=\"app\" style=\"width:1000px;margin:100px auto;\">\r\n    <br/>\r\n  <br/>\r\n  <br/>\r\n  <br/>\r\n  <br/>\r\n  <br/>\r\n  <br/>\r\n  <br/>\r\n  <br/>\r\n  <br/>\r\n  <br/>\r\n  <br/>\r\n  <br/>\r\n  <br/>\r\n  <br/>\r\n  <br/>\r\n  <br/>\r\n  <br/>\r\n  <br/>\r\n  <br/>\r\n  <br/>\r\n  <br/>\r\n  <br/>\r\n  <br/>\r\n  <br/>\r\n  <br/>\r\n  <br/>\r\n  <br/>\r\n  <br/>\r\n  <br/>\r\n  <br/>\r\n  <br/>\r\n  <br/>\r\n  <br/>\r\n  <br/>\r\n  <br/>\r\n  <h2 class=\"title\">alert</h2>\r\n  <el-button type=\"primary\" @click=\"submitHandle\">提交</el-button>\r\n  <h2 class=\"title\">confirm</h2>\r\n  <el-button type=\"primary\" @click=\"confirmHandle\">删除</el-button>\r\n  <h2 class=\"title\">msg</h2>\r\n  <el-button type=\"primary\" @click=\"msgHandle\">msg</el-button>\r\n  <el-button type=\"primary\" @click=\"msg1Handle\">带回调</el-button>\r\n  <h2 class=\"title\">loading</h2>\r\n  <el-button type=\"primary\" @click=\"loadingHandle\">默认样式</el-button>\r\n  <h2 class=\"title\">tips</h2>\r\n  <el-button type=\"primary\" id=\"tips\" @click=\"tipsHandle\">上</el-button>\r\n  <el-button type=\"primary\" id=\"tips1\" @mouseenter.native=\"tips1Handle\">右</el-button>\r\n  <el-button type=\"primary\" id=\"tips2\" @click=\"tips2Handle\">下</el-button>\r\n  <el-button type=\"primary\" id=\"tips3\" @click=\"tips3Handle\">左-自定义样式</el-button>\r\n  <h2 class=\"title\">page</h2>\r\n  <el-button type=\"primary\" id=\"tips\" @click=\"pageHandle\">自定义</el-button>\r\n</div>\r\n</template>\r\n\r\n<script>\r\nimport tools from \"./js/tools.js\";\r\nimport formComp from \"./form.vue\";\r\n\r\nexport default {\r\n  data() {\r\n    return {};\r\n  },\r\n  components: {\r\n    \"base-form\": formComp\r\n  },\r\n  async mounted() {\r\n    let ids = [];\r\n    for (let i = 0; i < 5; i++) {\r\n      await tools.sleep(10);\r\n      let id = this.loadingHandle();\r\n      ids.push(id);\r\n    }\r\n    for (let i = 0; i < 5; i++) {\r\n      await tools.sleep(200);\r\n      this.$layer.close(ids[i]);\r\n    }\r\n    this.$on(\"asd\", function(val) {\r\n      this.$layer.msg(val);\r\n    });\r\n  },\r\n  methods: {\r\n    submitHandle: function() {\r\n      let id = this.$layer.alert(\r\n        \"this is demo!!!<br/>this is demo!!!<br/>this is demo!!!<br/>this is demo!!!<br/>this is demo!!!<br/>this is demo!!!<br/>this is demo!!!<br/>this is demo!!!this is demo!!!this is demo!!!this is demo!!!this is demo!!!this is demo!!!this is demo!!!this is demo!!!this is demo!!!\",\r\n        {\r\n          shade: true\r\n        },\r\n        () => {\r\n          alert(1);\r\n          this.$layer.close(id);\r\n        }\r\n      );\r\n    },\r\n    confirmHandle: function() {\r\n      let id = this.$layer.confirm(\r\n        \"确定要<br/>删除吗？\",\r\n        () => {\r\n          this.$layer.msg(\"执行了删除\");\r\n          this.$layer.close(id);\r\n        },\r\n        () => {\r\n          this.$layer.msg(\"执行取消\");\r\n          this.$layer.close(id);\r\n        }\r\n      );\r\n    },\r\n    msgHandle: function() {\r\n      let id = this.$layer.msg(\"弱弱的提示\");\r\n    },\r\n    msg1Handle: function() {\r\n      let id = this.$layer.msg(\r\n        \"5s后刷新页面\",\r\n        {\r\n          time: 5\r\n        },\r\n        () => {\r\n          this.$layer.close(id);\r\n        }\r\n      );\r\n    },\r\n    loadingHandle: function() {\r\n      let id = this.$layer.loading({\r\n        time: 500\r\n      });\r\n      return id;\r\n    },\r\n    tipsHandle: function() {\r\n      let id = this.$layer.tips(\"在很久很久以前\", \"#tips\", {\r\n        tips: 0,\r\n        time: 100\r\n      });\r\n    },\r\n    tips1Handle: function() {\r\n      let id = this.$layer.tips(\r\n        \"在很久很久以前，在很久很久以前，在很久很久以前，在很久很久以前，在很久很久以前，在很久很久以前，\",\r\n        \"#tips1\",\r\n        {\r\n          tips: 1,\r\n          time: 100\r\n        }\r\n      );\r\n    },\r\n    tips2Handle: function() {\r\n      let id = this.$layer.tips(\r\n        \"在很久很久以前，在很久很久以前，在很久很久以前，在很久很久以前，在很久很久以前，在很久很久以前，\",\r\n        \"#tips2\",\r\n        {\r\n          tips: 2\r\n        }\r\n      );\r\n    },\r\n    tips3Handle: function() {\r\n      let id = this.$layer.tips(\r\n        \"在很久很久以前，在很久很久以前，在很久很久以前，在很久很久以前，在很久很久以前，在很久很久以前，\",\r\n        \"#tips3\",\r\n        {\r\n          tips: [\r\n            3,\r\n            {\r\n              selfa: true\r\n            }\r\n          ],\r\n          time: 10\r\n        }\r\n      );\r\n    },\r\n    pageHandle: function() {\r\n      let ids = this.$layer.iframe({\r\n        content: {\r\n          content: formComp,\r\n          parent: this,\r\n          data: {\r\n            check: \"aaaaaaaaxxxx\"\r\n          }\r\n        },\r\n        area: [\"900px\", \"600px\"],\r\n        title: \"\",\r\n        shade: false\r\n      });\r\n    }\r\n  }\r\n};\r\n</script>\r\n"},"lineCount":null},"css":".title {\n  height: 30px;\n  line-height: 30px;\n  margin-top: 30px;\n  margin-bottom: 10px;\n}\n"},"hash":"bdcf71fed573a6ac532625a8c7c2b9c5","cacheData":{"env":{}}}